Workbook

Sheet Sheet1
A1: Symbol | B1: Company Name | C1: Industry | D1: Revenue | E1: Total Cost | F1: Total Tax Paid | G1: Profit | H1: Inventories | I1: Cash | J1: Total Current Assets | K1: Unit
A2: TATAMOTORS | B2: Tata Motors | C2: Automobile | D2: =Raw!D2*10 -> 478744.3 | E2: =Raw!E2*10 -> 515790.8 | F2: =Raw!F2*10 -> 828.7 | G2: =Raw!G2*10 -> -23954.4 | H2: =Raw!H2*10 -> 45517.1 | I2: =Raw!I2*10 -> 43189.4 | J2: =Raw!J2*10 -> 158545.9 | K2: million
A3: BAJAJ-AUTO | B3: Bajaj Auto | C3: Automobile | D3: =Raw!D3*10 -> 290175.4 | E3: =Raw!E3*10 -> 230785.4 | F3: =Raw!F3*10 -> 13844.1 | G3: =Raw!G3*10 -> 45545.9 | H3: =Raw!H3*10 -> 14938.9 | I3: =Raw!I3*10 -> 5273.6 | J3: =Raw!J3*10 -> 141751.3 | K3: million
A4: EICHERMOT | B4: Eicher Motors Ltd | C4: Automobile | D4: =Raw!D4*10 -> 86190.4 | E4: =Raw!E4*10 -> 72785.6 | F4: =Raw!F4*10 -> 4536.1 | G4: =Raw!G4*10 -> 13297 | H4: =Raw!H4*10 -> 7691.3 | I4: =Raw!I4*10 -> 57989.1 | J4: =Raw!J4*10 -> 87476.9 | K4: million
A5: HEROMOTOCO | B5: Hero MotoCorp | C5: Automobile | D5: =Raw!D5*10 -> 313804.7 | E5: =Raw!E5*10 -> 274800.9 | F5: =Raw!F5*10 -> 9361.8 | G5: =Raw!G5*10 -> 29642 | H5: =Raw!H5*10 -> 14695.5 | I5: =Raw!I5*10 -> 2571.5 | J5: =Raw!J5*10 -> 109527.9 | K5: million
A6: M&M | B6: Mahindra & Mahindra | C6: Automobile | D6: =Raw!D6*10 -> 462622.9 | E6: =Raw!E6*10 -> 411589.4 | F6: =Raw!F6*10 -> 11916.2 | G6: =Raw!G6*10 -> 2484.6 | H6: =Raw!H6*10 -> 39554.7 | I6: =Raw!I6*10 -> 62554.2 | J6: =Raw!J6*10 -> 203123 | K6: million
A7: MARUTI | B7: Maruti Suzuki India | C7: Automobile | D7: =Raw!D7*10 -> 733368 | E7: =Raw!E7*10 -> 681774 | F7: =Raw!F7*10 -> 9297 | G7: =Raw!G7*10 -> 42297 | H7: =Raw!H7*10 -> 30500 | I7: =Raw!I7*10 -> 30364 | J7: =Raw!J7*10 -> 185267 | K7: million
A8: GRASIM | B8: Grasim Industries | C8: Cement Sector | D8: =Raw!D8*10 -> 129000.4 | E8: =Raw!E8*10 -> 118861.6 | F8: =Raw!F8*10 -> 1224.4 | G8: =Raw!G8*10 -> 9050 | H8: =Raw!H8*10 -> 21789.9 | I8: =Raw!I8*10 -> 1326.9 | J8: =Raw!J8*10 -> 86382.3 | K8: million
A9: ULTRACEMCO | B9: Ultratech Cement | C9: Cement Sector | D9: =Raw!D9*10 -> 439770.2 | E9: =Raw!E9*10 -> 359169.5 | F9: =Raw!F9*10 -> 25540 | G9: =Raw!G9*10 -> 53420.7 | H9: =Raw!H9*10 -> 37220.5 | I9: =Raw!I9*10 -> 18765.5 | J9: =Raw!J9*10 -> 229923.7 | K9: million
A10: SHREECEM | B10: Shree Cement | C10: Cement sector | D10: =Raw!D10*10 -> 130463.9 | E10: =Raw!E10*10 -> 100206.7 | F10: =Raw!F10*10 -> 30257.2 | G10: =Raw!G10*10 -> 23119.3 | H10: =Raw!H10*10 -> 14771.7 | I10: =Raw!I10*10 -> 2097.6 | J10: =Raw!J10*10 -> 71994.6 | K10: million
A11: ASIANPAINT | B11: Asian Paints Ltd | C11: Consumer Goods | D11: =Raw!D11*10 -> 188831.8 | E11: =Raw!E11*10 -> 147928 | F11: =Raw!F11*10 -> 10378.7 | G11: =Raw!G11*10 -> 30525.1 | H11: =Raw!H11*10 -> 31246.1 | I11: =Raw!I11*10 -> 1349.1 | J11: =Raw!J11*10 -> 99565.4 | K11: million
A12: ITC | B12: ITC | C12: Consumer Goods | D12: =Raw!D12*10 -> 487361 | E12: =Raw!E12*10 -> 315719.5 | F12: =Raw!F12*10 -> 42296.6 | G12: =Raw!G12*10 -> 129344.9 | H12: =Raw!H12*10 -> 94708.7 | I12: =Raw!I12*10 -> 40015 | J12: =Raw!J12*10 -> 318154.2 | K12: million
A13: BRITANNIA | B13: Britannia Industries | C13: Consumer Goods | D13: =Raw!D13*10 -> 126716.2 | E13: =Raw!E13*10 -> 102921.8 | F13: =Raw!F13*10 -> 6194.1 | G13: =Raw!G13*10 -> 17600.3 | H13: =Raw!H13*10 -> 9912.8 | I13: =Raw!I13*10 -> 1108 | J13: =Raw!J13*10 -> 40149.3 | K13: million
... A38: DIVISLAB | B38: Divis Laboratories Ltd | C38: Pharma sector | D38: =Raw!D38*10 -> 68611.4 | E38: =Raw!E38*10 -> 42332.7 | F38: =Raw!F38*10 -> 6731.5 | G38: =Raw!G38*10 -> 19547.2 | H38: =Raw!H38*10 -> 20427 | I38: =Raw!I38*10 -> 21420.1 | J38: =Raw!J38*10 -> 61253.1 | K38: million

Sheet Raw
A1: Symbol | B1: Company Name | C1: Industry | D1: Revenue | E1: Total Cost | F1: Total tax paid | G1: Profit | H1: Inventories | I1: Cash | J1: Total Current Assets | K1: Unit
A2: TATAMOTORS | B2: Tata Motors | C2: Automobile | D2: 47874.43 | E2: 51579.08 | F2: 82.87 | G2: -2395.44 | H2: 4551.71 | I2: 4318.94 | J2: 15854.59 | K2: Crore
A3: BAJAJ-AUTO | B3: Bajaj Auto | C3: Automobile | D3: 29017.54 | E3: 23078.54 | F3: 1384.41 | G3: 4554.59 | H3: 1493.89 | I3: 527.36 | J3: 14175.13 | K3: Crore
A4: EICHERMOT | B4: Eicher Motors Ltd | C4: Automobile | D4: 8619.04 | E4: 7278.56 | F4: 453.61 | G4: 1329.7 | H4: 769.13 | I4: 5798.91 | J4: 8747.69 | K4: Crore
A5: HEROMOTOCO | B5: Hero MotoCorp | C5: Automobile | D5: 31380.47 | E5: 27480.09 | F5: 936.18 | G5: 2964.2 | H5: 1469.55 | I5: 257.15 | J5: 10952.79 | K5: Crore
A6: M&M | B6: Mahindra & Mahindra | C6: Automobile | D6: 46262.29 | E6: 41158.94 | F6: 1191.62 | G6: 248.46 | H6: 3955.47 | I6: 6255.42 | J6: 20312.3 | K6: Crore
A7: MARUTI | B7: Maruti Suzuki India | C7: Automobile | D7: 73336.8 | E7: 68177.4 | F7: 929.7 | G7: 4229.7 | H7: 3050 | I7: 3036.4 | J7: 18526.7 | K7: Crore
A8: GRASIM | B8: Grasim Industries | C8: Cement Sector | D8: 12900.04 | E8: 11886.16 | F8: 122.44 | G8: 905 | H8: 2178.99 | I8: 132.69 | J8: 8638.23 | K8: Crore
A9: ULTRACEMCO | B9: Ultratech Cement | C9: Cement Sector | D9: 43977.02 | E9: 35916.95 | F9: 2554 | G9: 5342.07 | H9: 3722.05 | I9: 1876.55 | J9: 22992.37 | K9: Crore
A10: SHREECEM | B10: Shree Cement | C10: Cement sector | D10: 13046.39 | E10: 10020.67 | F10: 3025.72 | G10: 2311.93 | H10: 1477.17 | I10: 209.76 | J10: 7199.46 | K10: Crore
A11: ASIANPAINT | B11: Asian Paints Ltd | C11: Consumer Goods | D11: 18883.18 | E11: 14792.8 | F11: 1037.87 | G11: 3052.51 | H11: 3124.61 | I11: 134.91 | J11: 9956.54 | K11: Crore
A12: ITC | B12: ITC | C12: Consumer Goods | D12: 48736.1 | E12: 31571.95 | F12: 4229.66 | G12: 12934.49 | H12: 9470.87 | I12: 4001.5 | J12: 31815.42 | K12: Crore
A13: BRITANNIA | B13: Britannia Industries | C13: Consumer Goods | D13: 12671.62 | E13: 10292.18 | F13: 619.41 | G13: 1760.03 | H13: 991.28 | I13: 110.8 | J13: 4014.93 | K13: Crore
... A38: DIVISLAB | B38: Divis Laboratories Ltd | C38: Pharma sector | D38: 6861.14 | E38: 4233.27 | F38: 673.15 | G38: 1954.72 | H38: 2042.7 | I38: 2142.01 | J38: 6125.31 | K38: Crore
